tapl_lang.py
tapl_lang-0.1.dist-info/LICENSE
tapl_lang-0.1.dist-info/WHEEL
tapl_lang-0.1.dist-info/METADATA
tapl_lang-0.1.dist-info/RECORD
